bin/api-ms-win-core-console-l1-1-0.dll
bin/api-ms-win-core-console-l1-2-0.dll
bin/api-ms-win-core-datetime-l1-1-0.dll
bin/api-ms-win-core-debug-l1-1-0.dll
bin/api-ms-win-core-errorhandling-l1-1-0.dll
bin/api-ms-win-core-fibers-l1-1-0.dll
bin/api-ms-win-core-fibers-l1-1-1.dll
bin/api-ms-win-core-file-l1-1-0.dll
bin/api-ms-win-core-file-l1-2-0.dll
bin/api-ms-win-core-file-l2-1-0.dll
bin/api-ms-win-core-handle-l1-1-0.dll
bin/api-ms-win-core-heap-l1-1-0.dll
bin/api-ms-win-core-interlocked-l1-1-0.dll
bin/api-ms-win-core-kernel32-legacy-l1-1-1.dll
bin/api-ms-win-core-libraryloader-l1-1-0.dll
bin/api-ms-win-core-localization-l1-2-0.dll
bin/api-ms-win-core-memory-l1-1-0.dll
bin/api-ms-win-core-namedpipe-l1-1-0.dll
bin/api-ms-win-core-processenvironment-l1-1-0.dll
bin/api-ms-win-core-processthreads-l1-1-0.dll
bin/api-ms-win-core-processthreads-l1-1-1.dll
bin/api-ms-win-core-profile-l1-1-0.dll
bin/api-ms-win-core-rtlsupport-l1-1-0.dll
bin/api-ms-win-core-string-l1-1-0.dll
bin/api-ms-win-core-synch-l1-1-0.dll
bin/api-ms-win-core-synch-l1-2-0.dll
bin/api-ms-win-core-sysinfo-l1-1-0.dll
bin/api-ms-win-core-sysinfo-l1-2-0.dll
bin/api-ms-win-core-timezone-l1-1-0.dll
bin/api-ms-win-core-util-l1-1-0.dll
bin/api-ms-win-crt-conio-l1-1-0.dll
bin/api-ms-win-crt-convert-l1-1-0.dll
bin/api-ms-win-crt-environment-l1-1-0.dll
bin/api-ms-win-crt-filesystem-l1-1-0.dll
bin/api-ms-win-crt-heap-l1-1-0.dll
bin/api-ms-win-crt-locale-l1-1-0.dll
bin/api-ms-win-crt-math-l1-1-0.dll
bin/api-ms-win-crt-multibyte-l1-1-0.dll
bin/api-ms-win-crt-private-l1-1-0.dll
bin/api-ms-win-crt-process-l1-1-0.dll
bin/api-ms-win-crt-runtime-l1-1-0.dll
bin/api-ms-win-crt-stdio-l1-1-0.dll
bin/api-ms-win-crt-string-l1-1-0.dll
bin/api-ms-win-crt-time-l1-1-0.dll
bin/api-ms-win-crt-utility-l1-1-0.dll
bin/concrt140.dll
bin/msvcp140.dll
bin/msvcp140_1.dll
bin/msvcp140_2.dll
bin/msvcp140_atomic_wait.dll
bin/msvcp140_codecvt_ids.dll
bin/ucrtbase.dll
bin/vcruntime140.dll
bin/vcruntime140_1.dll
prism/__init__.py
prismatoid-0.7.0.dist-info/METADATA
prismatoid-0.7.0.dist-info/WHEEL
prismatoid-0.7.0.dist-info/licenses/LICENSE
prismatoid-0.7.0.dist-info/licenses/NOTICE
prismatoid-0.7.0.dist-info/licenses/LICENSES/nvdaController/lgpl-2.1.txt
prismatoid-0.7.0.dist-info/licenses/LICENSES/nvgt/LICENSE.md
prismatoid-0.7.0.dist-info/licenses/LICENSES/prism/mpl-2.0.txt
prismatoid-0.7.0.dist-info/licenses/LICENSES/simdutf/apache-2.0.txt
prismatoid-0.7.0.dist-info/RECORD
