Metadata-Version: 2.4
Name: prismatoid
Version: 0.7.0
Summary: The Platform-Agnostic Reader Interface for Speech and Messages
Author-Email: Ethin Probst <ethindp@pm.me>
License-Expression: MPL-2.0
License-File: LICENSE
License-File: LICENSES/nvdaController/lgpl-2.1.txt
License-File: LICENSES/nvgt/LICENSE.md
License-File: LICENSES/prism/mpl-2.0.txt
License-File: LICENSES/simdutf/apache-2.0.txt
License-File: NOTICE
Requires-Python: >=3.10
Requires-Dist: cffi>=2.0.0
Requires-Dist: win32more>=0.8.0; sys_platform == "win32"
